CHANGES.rst
DESCRIPTION.rst
LICENSE
MANIFEST.in
README.md
setup.py
src/ldc/__init__.py
src/ldc/blah.py
src/ldc/class_lister.py
src/ldc/core.py
src/ldc/help.py
src/ldc/registry.py
src/ldc/text_utils.py
src/ldc/utils.py
src/ldc/api/__init__.py
src/ldc/api/_downloader.py
src/ldc/api/_filter.py
src/ldc/api/_io.py
src/ldc/api/pretrain.py
src/ldc/api/translation.py
src/ldc/api/supervised/__init__.py
src/ldc/api/supervised/classification.py
src/ldc/api/supervised/pairs.py
src/ldc/downloader/__init__.py
src/ldc/downloader/_huggingface.py
src/ldc/filter/__init__.py
src/ldc/filter/_assemble_sentences.py
src/ldc/filter/_change_case.py
src/ldc/filter/_discard_by_name.py
src/ldc/filter/_file_filter.py
src/ldc/filter/_find_substr.py
src/ldc/filter/_inspect.py
src/ldc/filter/_keyword.py
src/ldc/filter/_llama2_to_pairs.py
src/ldc/filter/_max_records.py
src/ldc/filter/_metadata.py
src/ldc/filter/_metadata_from_name.py
src/ldc/filter/_pairs_to_llama2.py
src/ldc/filter/_pairs_to_pretrain.py
src/ldc/filter/_pretrain_sentences_to_classification.py
src/ldc/filter/_pretrain_sentences_to_pairs.py
src/ldc/filter/_randomize_records.py
src/ldc/filter/_record_files.py
src/ldc/filter/_record_window.py
src/ldc/filter/_remove_blocks.py
src/ldc/filter/_remove_empty.py
src/ldc/filter/_remove_patterns.py
src/ldc/filter/_remove_strings.py
src/ldc/filter/_replace_patterns.py
src/ldc/filter/_reset_ids.py
src/ldc/filter/_set_placeholder.py
src/ldc/filter/_skip_duplicate_ids.py
src/ldc/filter/_skip_duplicate_text.py
src/ldc/filter/_split_records.py
src/ldc/filter/_strip_strings.py
src/ldc/filter/_tee.py
src/ldc/filter/_text_length.py
src/ldc/filter/_text_stats.py
src/ldc/filter/_to_llama2_format.py
src/ldc/filter/_translation_to_pairs.py
src/ldc/filter/_translation_to_pretrain.py
src/ldc/pretrain/__init__.py
src/ldc/pretrain/_csv.py
src/ldc/pretrain/_jsonlines.py
src/ldc/pretrain/_max_length.py
src/ldc/pretrain/_parquet.py
src/ldc/pretrain/_sentences.py
src/ldc/pretrain/_split.py
src/llm_dataset_converter.egg-info/PKG-INFO
src/llm_dataset_converter.egg-info/SOURCES.txt
src/llm_dataset_converter.egg-info/dependency_links.txt
src/llm_dataset_converter.egg-info/entry_points.txt
src/llm_dataset_converter.egg-info/requires.txt
src/llm_dataset_converter.egg-info/top_level.txt