Metadata-Version: 2.1
Name: llm-dataset-converter
Version: 0.2.7
Summary: Python3 library for converting between various LLM dataset formats.
Home-page: https://github.com/waikato-llm/llm-dataset-converter
Author: Peter Reutemann
Author-email: fracpete@waikato.ac.nz
License: MIT License
Classifier: Development Status :: 4 - Beta
Classifier: License :: OSI Approved :: MIT License
Classifier: Topic :: Scientific/Engineering :: Artificial Intelligence
Classifier: Programming Language :: Python :: 3
License-File: LICENSE
